neoml/AutoDiff.py
neoml/Blob.py
neoml/BytePairEncoder.py
neoml/Clustering.py
neoml/CrossValidation.py
neoml/DecisionTree.py
neoml/DifferentialEvolution.py
neoml/GradientBoost.py
neoml/Linear.py
neoml/MathEngine.py
neoml/NeoML.dll
neoml/NeoMathEngine.dll
neoml/NeoMathEngineAvx.dll
neoml/NeoOnnx.dll
neoml/PCA.py
neoml/PythonWrapper.cp38-win_amd64.pyd
neoml/Random.py
neoml/SVM.py
neoml/Utils.py
neoml/__init__.py
neoml/Dnn/AccumulativeLookup.py
neoml/Dnn/Accuracy.py
neoml/Dnn/Activation.py
neoml/Dnn/AddToObject.py
neoml/Dnn/Argmax.py
neoml/Dnn/AttentionDecoder.py
neoml/Dnn/BatchNormalization.py
neoml/Dnn/BertConv.py
neoml/Dnn/Binarization.py
neoml/Dnn/Broadcast.py
neoml/Dnn/Cast.py
neoml/Dnn/Concat.py
neoml/Dnn/Conv.py
neoml/Dnn/Crf.py
neoml/Dnn/Ctc.py
neoml/Dnn/CumSum.py
neoml/Dnn/Data.py
neoml/Dnn/Dnn.py
neoml/Dnn/DnnDistributed.py
neoml/Dnn/DotProduct.py
neoml/Dnn/Dropout.py
neoml/Dnn/Eltwise.py
neoml/Dnn/FullyConnected.py
neoml/Dnn/Gru.py
neoml/Dnn/ImageConversion.py
neoml/Dnn/IndRnn.py
neoml/Dnn/Initializer.py
neoml/Dnn/Irnn.py
neoml/Dnn/Logical.py
neoml/Dnn/Loss.py
neoml/Dnn/Lrn.py
neoml/Dnn/Lstm.py
neoml/Dnn/MatrixMultiplication.py
neoml/Dnn/MultichannelLookup.py
neoml/Dnn/MultiheadAttention.py
neoml/Dnn/ObjectNormalization.py
neoml/Dnn/Onnx.py
neoml/Dnn/Pooling.py
neoml/Dnn/PositionalEmbedding.py
neoml/Dnn/PrecisionRecall.py
neoml/Dnn/Qrnn.py
neoml/Dnn/Reorg.py
neoml/Dnn/RepeatSequence.py
neoml/Dnn/ScatterGather.py
neoml/Dnn/SequenceSum.py
neoml/Dnn/Sink.py
neoml/Dnn/Softmax.py
neoml/Dnn/Solver.py
neoml/Dnn/Source.py
neoml/Dnn/SpaceAndDepth.py
neoml/Dnn/Split.py
neoml/Dnn/SubSequence.py
neoml/Dnn/TiedEmbeddings.py
neoml/Dnn/Transform.py
neoml/Dnn/Transformer.py
neoml/Dnn/Transpose.py
neoml/Dnn/Upsampling2D.py
neoml/Dnn/__init__.py
neoml/Onnx/API.py
neoml/Onnx/Backend.py
neoml/Onnx/__init__.py
neoml-2.0.210.dist-info/METADATA
neoml-2.0.210.dist-info/WHEEL
neoml-2.0.210.dist-info/top_level.txt
neoml-2.0.210.dist-info/RECORD
