Metadata-Version: 2.1
Name: neoml
Version: 2.0.210
Summary: NeoML python bindings
Home-page: http://github.com/neoml-lib/neoml
Requires-Dist: numpy >=1.19.1
Requires-Dist: scipy >=1.5.2
Requires-Dist: onnx ==1.14.1
Requires-Dist: protobuf ==3.20.*
